lcrl/__init__.py
lcrl/train.py
lcrl/animator/__init__.py
lcrl/animator/animator.py
lcrl/automata/__init__.py
lcrl/automata/cart_pole.py
lcrl/automata/frozen_lake_1_2_3.py
lcrl/automata/frozen_lake_4_5_6.py
lcrl/automata/goal1_or_goal2.py
lcrl/automata/goal1_then_goal2.py
lcrl/automata/ldba.py
lcrl/automata/mars_rover_1_3.py
lcrl/automata/mars_rover_2_4.py
lcrl/automata/minecraft_1.py
lcrl/automata/minecraft_2.py
lcrl/automata/minecraft_3.py
lcrl/automata/minecraft_4.py
lcrl/automata/minecraft_5.py
lcrl/automata/minecraft_6.py
lcrl/automata/minecraft_7.py
lcrl/automata/pacman.py
lcrl/automata/slp_easy.py
lcrl/automata/slp_hard.py
lcrl/automata/surveillance.py
lcrl/core/__init__.py
lcrl/core/lcrl_core.py
lcrl/environments/CartPole.py
lcrl/environments/MarsRoverCA.py
lcrl/environments/MarsRoverDA.py
lcrl/environments/SlipperyGrid.py
lcrl/environments/__init__.py
lcrl/environments/cart_pole.py
lcrl/environments/frozen_lake_1.py
lcrl/environments/frozen_lake_2.py
lcrl/environments/frozen_lake_3.py
lcrl/environments/frozen_lake_4.py
lcrl/environments/frozen_lake_4x4.py
lcrl/environments/frozen_lake_5.py
lcrl/environments/frozen_lake_6.py
lcrl/environments/frozen_lake_8x8.py
lcrl/environments/gridworld_1.py
lcrl/environments/gridworld_2.py
lcrl/environments/gridworld_3.py
lcrl/environments/mars_rover_1_2.py
lcrl/environments/mars_rover_3_4.py
lcrl/environments/minecraft.py
lcrl/environments/pacman.py
lcrl/environments/pacman_f.py
lcrl/environments/pacman_g.py
lcrl/environments/robot_surv.py
lcrl/environments/slp_lrg.py
lcrl/environments/slp_med.py
lcrl/environments/slp_sml.py
lcrl/environments/layouts/__init__.py
lcrl/environments/layouts/large.py
lcrl/environments/layouts/marsrover_1.png
lcrl/environments/layouts/small.py
lcrl-0.0.9.2.dist-info/LICENSE
lcrl-0.0.9.2.dist-info/METADATA
lcrl-0.0.9.2.dist-info/WHEEL
lcrl-0.0.9.2.dist-info/top_level.txt
lcrl-0.0.9.2.dist-info/RECORD
