Metadata-Version: 2.1
Name: lcrl
Version: 0.0.9.2
Summary: Logically-Constrained Reinforcement Learning
Home-page: https://github.com/grockious/lcrl
Author: Hosein Hasanbeig
Author-email: Hosein Hasanbeig <hosein.hasanbeig@icloud.com>
License: The MIT License
Project-URL: Homepage, https://github.com/grockious/lcrl
Keywords: rl,logic,environment,agent
Classifier: Programming Language :: Python :: 3
Classifier: License :: OSI Approved :: MIT License
Classifier: Operating System :: OS Independent
Requires-Python: >=3.8
License-File: LICENSE
Requires-Dist: numpy
Requires-Dist: matplotlib
Requires-Dist: dill >=0.3.2
Requires-Dist: imageio
Requires-Dist: tqdm
Requires-Dist: tensorflow >=2
